[{"title":"국민연금 제친 개인투자자…삼성전자 지분율 10% 첫 `돌파`","link":"https://news.naver.com/main/read.nhn?mode=LSD&mid=sec&sid1=101&oid=018&aid=0004919077","description":"개인투자자들이 올 들어 삼성전자(<b>005930</b>)를 19조원이상 대규모 매수하면서 개인들의 삼성전자 지분율이 처음으로 10%를 돌파했다. 2일 금융투자업계와 한국거래소에 따르면 지난달 30일 기준 개인투자자가 보유한... ","datetime":"2021-05-02 10:44:00"},{"title":"지배구조 위협 '삼성생명법'...통과땐 전자 지분 6.6% 처분해야","link":"https://news.naver.com/main/read.nhn?mode=LSD&mid=sec&sid1=101&oid=011&aid=0003905031","description":"이재용 삼성전자(<b>005930</b>) 부회장 중심으로 재편된 삼성그룹 지배력을 두고 국회에 계류 중인 ‘삼성생명(032830)법’이 변수로 급부상하고 있다. 해당 법이 통과될 경우 이 부회장이 고(故) 이건희 삼성그룹 회장으로부터... ","datetime":"2021-05-02 09:16:00"},{"title":"삼성家 이서현, 삼성공익재단에 3억 기부","link":"https://news.naver.com/main/read.nhn?mode=LSD&mid=sec&sid1=101&oid=011&aid=0003904973","description":"최대 금액을 기부한 삼성전자(<b>005930</b>)는 265억 원을 출연했다. 이는 전체 기부금의 절반 이상이다. 삼성디스플레이는 16억 원, 삼성물산(028260)과 삼성전기(009150)는 각각 6억 원씩 냈다. 이 이사장 외에 삼성그룹의 전... ","datetime":"2021-05-02 08:29:00"},{"title":"'황금 분할' 주식 상속…이재용 '뉴 삼성' 기반 단단히 다졌다","link":"https://news.naver.com/main/read.nhn?mode=LSD&mid=sec&sid1=101&oid=018&aid=0004918804","description":"2일 삼성과 금융감독원에 따르면 이건희 회장이 보유하던 삼성전자(<b>005930</b>), 삼성물산(028260), 삼성SDS(018260) 주식은 홍라희 여사와 이재용 부회장, 이부진 호텔신라 사장, 이서현 삼성복지재단 이사장이 법정 비율(홍 여사... ","datetime":"2021-05-02 05:40:00"},{"title":"상속 마무리한 이재용 '산 넘어 산'…재판 대응하며 투자 결정해야","link":"https://news.naver.com/main/read.nhn?mode=LSD&mid=sec&sid1=101&oid=018&aid=0004918807","description":"이런 가운데 이 부회장은 삼성전자(<b>005930</b>)의 주요 투자도 결정해야 한다. 삼성전자는 미국에 신규 파운드리(반도체 위탁생산) 공장 신설을 검토 중이며, 국내 평택캠퍼스에는 P3 라인 투자 결정을 앞두고 있다. 오스틴... ","datetime":"2021-05-02 05:40:00"},{"title":"삼성家 이서현, 삼성공익재단에 3억원 기부","link":"https://news.naver.com/main/read.nhn?mode=LSD&mid=sec&sid1=004&oid=366&aid=0000711051","description":"이 가운데 삼성전자(<b>005930</b>)가 265억원을 출연해 전체 기부금의 절반 이상을 차지했다. 삼성디스플레이는 16억원, 삼성물산(028260)은 11억원, 삼성SDI(006400)와 삼성전기(009150)는 각각 6억원씩 기부금을 출연했다. 전·현직... ","datetime":"2021-05-02 04:34:00"},{"title":"이재용 중심의 삼성 지배구조…홍라희가 ‘경영권 안정 조력자'","link":"https://news.naver.com/main/read.nhn?mode=LSD&mid=sec&sid1=004&oid=366&aid=0000711048","description":"삼성생명 지분은 이재용 삼성전자 부회장에게 몰아줘 ‘이재용 부회장→삼성물산(028260)→삼성생명(032830)→삼성전자(<b>005930</b>)’로 이어지는 지배구조는 공고히하고, 나머지는 법정비율대로 상속하는 방안을 택했다.... ","datetime":"2021-05-02 03:18:00"},{"title":"“류준열이 왜?”···삼성전자, ‘Neo Life' 영상 공개","link":"https://news.naver.com/main/read.nhn?mode=LSD&mid=sec&sid1=101&oid=011&aid=0003904874","description":"삼성전자(<b>005930</b>)가 ‘Neo QLED 8K’를 통해 소비자들의 일상을 풍요롭게 만들어 준다는 메시지를 담은 새로운 영상 ‘Neo LIFE’를 1일 공개했다. 해당 영상에는 배우 이시영, 류준열 씨가 참여했다. 삼성전자는 Neo QLED... ","datetime":"2021-05-02 02:23:00"},{"title":"삼성 '갤럭시북 프로' 신규 기능 기존 갤럭시북에서도 쓴다","link":"https://news.naver.com/main/read.nhn?mode=LSD&mid=sec&sid1=101&oid=018&aid=0004918498","description":"삼성전자(<b>005930</b>)는 지난달 28일 ‘삼성 갤럭시 언팩’에서 공개한 노트북 신제품 ‘갤럭시 북 프로(Galaxy Book Pro)’ 시리즈의 신규 기능을 기존 ‘갤럭시 북’ 시리즈에도 지원한다고 2일 밝혔다. 삼성전자는 △‘갤럭시... ","datetime":"2021-05-02 02:02:00"}]