[{"title":"&quot;미래산업 전쟁 속 삼성 역할론 절실···'이재용 사면' 공감대 형성을&quot;","link":"https://news.naver.com/main/read.nhn?mode=LSD&mid=sec&sid1=101&oid=011&aid=0003917094","description":"문재인 대통령과 4대 그룹 총수가 얼굴을 맞대는 6월 2일 회동에서 이재용 삼성전자(<b>005930</b>) 부회장의 사면에 대한 논의가 진행될지 관심이 모아지고 있다. 앞서 대한상공회의소와 한국경영자총협회 등 5개 주요... ","datetime":"2021-05-31 08:41:00"},{"title":"지난달 '급등' D램·낸드 값 5월엔 보합세…3분기 상승 전망","link":"https://news.naver.com/main/read.nhn?mode=LSD&mid=sec&sid1=101&oid=018&aid=0004943945","description":"트렌드포스에 따르면 올해 1분기 매출을 기준으로 전 세계 D램 시장 점유율은 삼성전자(<b>005930</b>)가 42.0％로 1위, SK하이닉스(000660)가 29.0％로 2위다. 낸드플래시의 경우 삼성이 점유율 33.5％로 1위, SK하이닉스는 4위(12.3... ","datetime":"2021-05-31 08:26:00"},{"title":"(영상)SNS·PPL이 대세…삼성, 적극 공략","link":"http://www.newstomato.com/ReadNews.aspx?no=1048207&inflow=N","description":"삼성전자(<b>005930</b>)가 최근 스타의 소셜네트워크서비스(SNS)와 간접광고(PPL)를 적극 활용하고 있습니다. 스웨덴 축구스타 즐라탄 이브라히모비치(AC밀란)는 최근 자신의 인스타그램에 삼성 TV 네오(Neo)... ","datetime":"2021-05-31 08:22:00"},{"title":"美공장 증설·시스템반도체 투자↑…삼성, '의미 있는' M&amp;A 언제쯤?","link":"https://news.naver.com/main/read.nhn?mode=LSD&mid=sec&sid1=101&oid=018&aid=0004943876","description":"삼성전자(<b>005930</b>)가 미국 내 반도체 파운드리(위탁생산) 공장 증설과 시스템반도체 추가 투자 등의 계획을 발표한 가운데 올해 초부터 여러 차례 밝혀 온 대규모 인수합병(M&amp;A) 여부에도 관심이 쏠린다. 반도체업계에선... ","datetime":"2021-05-31 07:25:00"},{"title":"코스피, 외국인 사자에 3200선 탈환","link":"https://www.econovill.com/news/articleView.html?idxno=534313","description":"대장주인 삼성전자(<b>005930</b>)는 전 거래일 대비 400원(0.50%) 오른 8만500원에 거래를 마쳤다. SK하이닉스(000660)(1.60%)도 상승했다. LG화학(051910)(-1.56%), 삼성SDI(006400)(-3.91%)는 다소 큰 폭으로 내렸다. NAVER(035420)(1.26... ","datetime":"2021-05-31 07:12:00"},{"title":"[코스피 마감]개인·외국인 동반 '사자'에 3200선 회복","link":"https://news.naver.com/main/read.nhn?mode=LSD&mid=sec&sid1=101&oid=018&aid=0004943864","description":"대장주인 삼성전자(<b>005930</b>)는 1% 미만 올랐고 SK하이닉스(000660), 삼성전자우(005935), NAVER(035420)은 1%대 올랐다. 삼성바이오로직스(207940)가 2%대 올랐고 현대차(005380), 기아(000270)가 1%대, 카카오(035720), 셀트리온... ","datetime":"2021-05-31 07:10:00"},{"title":"TV 광고가 최고(?)…스타SNS·PPL에 뛰어든 삼성","link":"http://www.newstomato.com/ReadNews.aspx?no=1048127&inflow=N","description":"삼성전자(<b>005930</b>)가 최근 글로벌 스타의 소셜네트워크서비스(SNS)와 인기 드라마·예능 프로그램 간접광고(PPL)를 마케팅에 적극 활용하고 있다. 31일 관련업계에 따르면 스웨덴 축구스타 즐라탄 이브라히모비치(AC밀란)는... ","datetime":"2021-05-31 07:10:00"},{"title":"코스피, 외인·개인 순매수에 힘입어 20일만에 3,200 회복","link":"http://www.topstarnews.net/news/articleView.html?idxno=10532104","description":"시가총액 상위 종목 가운데에는 삼성전자[<b>005930</b>](0.50%)와 SK하이닉스[000660](1.60%), 네이버[035420](1.26%), 삼성바이오로직스[207940](2.18%), 현대차[005380](1.29%) 등이 올랐다. LG화학[051910](-1.56%)과 삼성SDI[006400]... ","datetime":"2021-05-31 07:10:00"},{"title":"코스피, 이틀째 외국인 순매수…3200선 상승 마감","link":"http://www.newstomato.com/ReadNews.aspx?no=1048138&inflow=N","description":"삼성전자(<b>005930</b>)가 0.5% 올랐으며 SK하이닉스(000660)(1.60%), NAVER(035420)(1.26%), 삼성바이오로직스(207940)(2.18%), 카카오(035720)(0.825), 현대차(005380)(1.29%) 등도 일제히 강세를 보였다. 반면 LG화학(051910)(-1.56%)과... ","datetime":"2021-05-31 06:48:00"},{"title":"&quot;삼성 이어 LG도&quot;…'年 300만대' 미니LED TV 격돌 임박","link":"https://news.naver.com/main/read.nhn?mode=LSD&mid=sec&sid1=101&oid=018&aid=0004943820","description":"LG전자(066570)의 미니 발광다이오드(LED) TV의 출시가 초읽기에 들어가면서 삼성전자(<b>005930</b>)와 격돌이 임박했다. 삼성전자에 이어 LG전자도 미니 LED TV 시장에 뛰어들면서 치열한 경쟁과 동시에 글로벌 시장... ","datetime":"2021-05-31 06:33:00"},{"title":"상승전환 코스피, '3200선' 코앞…시총상위 배터리株 하락세","link":"https://news.naver.com/main/read.nhn?mode=LSD&mid=sec&sid1=101&oid=018&aid=0004943732","description":"대장주인 삼성전자(<b>005930</b>)는 장 초반부터 보합권에서 등락을 이어가고 있고 SK하이닉스(000660), 삼성바이오로직스(207940)가 1%대 오름세다. 삼성전자우(005935), NAVER(035420), 카카오(035720), 현대차(005380)... ","datetime":"2021-05-31 05:34:00"},{"title":"라이트론, 삼성전자에 17억원 규모 장비용 광모듈 공급","link":"https://news.naver.com/main/read.nhn?mode=LSD&mid=sec&sid1=101&oid=018&aid=0004943710","description":"라이트론(069540)이 삼성전자(<b>005930</b>)에 17억원 규모의 기지국 장비용 광모듈을 공급하기로 했다고 31일 공시했다. 해당 규모는 지난해 매출액 대비 9%이다. 판매 및 공급지역은 베트남이고 계약기간은 지난... ","datetime":"2021-05-31 05:21:00"},{"title":"코스피, 3180선 혼조세 출발","link":"http://www.newstomato.com/ReadNews.aspx?no=1047936&inflow=N","description":"시가총액 상위 종목 중 삼성전자(<b>005930</b>)(-0.50%), SK하이닉스(000660)(-0.40%), LG화학(051910)(-2.40%) 등이 하락 출발했으며 NAVER(035420)(0.56%)와 삼성바이오로직스(207940)(0.73%) 등은 오르고 있다. 이날 같은 시각... ","datetime":"2021-05-31 01:18:00"},{"title":"Samsung Electronics ranked No. 1 in NAND market share in 1 quarte. Profi...","link":"http://www.g-enews.com/ko-kr/news/article/news_all/202105310935466478c4c1a19e2e_9/article.html","description":"In the first quarter of this year, the NAND flash market share of Samsung Electronics [<b>005930</b>] and SK Hynix [000660] rose from the fourth quarter of last year. Despite the weak NAND price, the... ","datetime":"2021-05-31 00:40:00"},{"title":"코스피, 시총상위株 혼조 속 보합권 출발…'3190선'","link":"https://news.naver.com/main/read.nhn?mode=LSD&mid=sec&sid1=101&oid=018&aid=0004943354","description":"대장주인 삼성전자(<b>005930</b>)는 약보합을 이어가고 있으며 SK하이닉스(000660), 삼성전자우(005935), NAVER(035420), 삼성바이오로직스(207940), 현대차(005380), 셀트리온(068270)은 1% 미만 상승 중이다. LG화학(051910), 카카오... ","datetime":"2021-05-31 00:13:00"}]