[{"title":"삼성전자, 5G 기지국용 자체 칩 3종 전격 공개…美·유럽 5G 장비 시장 승부수","link":"https://news.naver.com/main/read.nhn?mode=LSD&mid=sec&sid1=105&oid=366&aid=0000736878","description":"삼성 네트워크 사업부 단독 행사 이례적 개최 고성능 기지국 라인업, 특화망 솔루션까지 쏟아내 전경훈 사장 “전 세계 5G 시장 주도하겠다” 삼성전자(<b>005930</b>)에서 통신장비를 담당하는 네트워크 사업부가 22일 오후... ","datetime":"2021-06-22 14:01:00"},{"title":"'성능 두배, 크기 반으로' 삼성전자, 차세대 핵심칩으로 네트워크 초연결 시대...","link":"https://news.naver.com/main/read.nhn?mode=LSD&mid=sec&sid1=105&oid=011&aid=0003926859","description":"삼성전자(<b>005930</b>)가 5세대(5G) 기지국용 차세대 핵심칩 등을 앞세워 ‘글로벌 초연결 시대’를 주도하겠다는 청사진을 내놨다. 삼성전자의 기술력을 고스란히 담은 핵심칩을 활용해 크기는 줄이고 성능은 높인 ‘미래형... ","datetime":"2021-06-22 14:01:00"},{"title":"삼성전자, ‘5G 네트워크’ 막강 라인업 공개…6G도 주도 야심","link":"https://news.naver.com/main/read.nhn?mode=LSD&mid=sec&sid1=105&oid=018&aid=0004965066","description":"삼성전자 네트워크사업부장 전경훈 사장 (사진=삼성전자)[이데일리 이대호 기자] 삼성전자(<b>005930</b>)가 22일 글로벌 온라인 이벤트를 열고 5세대 이동통신(5G) 네트워크 솔루션을 대거 공개했다. 삼성전자... ","datetime":"2021-06-22 14:01:00"},{"title":"삼성전자, 올해 MWC서 갤럭시워치 변화 예고","link":"https://news.naver.com/main/read.nhn?mode=LSD&mid=sec&sid1=105&oid=018&aid=0004965047","description":"삼성전자(<b>005930</b>)가 오는 28일(스페인 현지시간) 개막하는 모바일월드콩그레스(MWC) 전시회에서 ‘삼성 갤럭시 버추얼 이벤트’를 진행한다고 22일 밝혔다. 삼성전자는 이 자리에서 갤럭시 기기 생태계를 소개한다.... ","datetime":"2021-06-22 10:51:00"},{"title":"'삼성전자 최연소 임원' 인도 출신 과학자 퇴사…&quot;9년 여정 끝&quot;","link":"https://news.naver.com/main/read.nhn?mode=LSD&mid=sec&sid1=101&oid=018&aid=0004964962","description":"삼성전자(<b>005930</b>)에서 ‘최연소 임원’ 타이틀을 달았던 인도 출신 과학자 프라나브 미스트리(사진·40)가 최근 회사를 떠났다. 22일 삼성전자에 따르면 삼성 사내 벤처 스타랩스(STAR Labs)장을 맡았던 미스트리 전무는... ","datetime":"2021-06-22 08:05:00"},{"title":"윤석열·최재형 저격한 김 총리 “대선 출마 비정상…안타깝다”","link":"https://news.naver.com/main/read.nhn?mode=LSD&mid=sec&sid1=100&oid=018&aid=0004964921","description":"김 총리는 정운천 국민의힘 의원이 이재용 삼성전자(<b>005930</b>) 부회장의 사면에 대해 질의하자 “경제단체들도 간담회에서 같은 취지로 말씀했다”며 “그런 내용을 정리해서 (문재인 대통령에게) 보고하겠다”고 말했다. 김... ","datetime":"2021-06-22 07:31:00"},{"title":"코스피, 외국인 순매수에 3260선 회복 …3263.88 마감","link":"https://www.econovill.com/news/articleView.html?idxno=537657","description":"대장주인 삼성전자(<b>005930</b>)는 전 거래일 대비 100원(0.13%) 오른 8만원에 거래를 마쳤다. SK하이닉스(000660)(-)는 보합을 기록했다. 카카오(035720)(2.58%)는 상승한 반면, NAVER(035420)(-1.51%)는 하락했다. LG화학(051910)... ","datetime":"2021-06-22 07:18:00"},{"title":"코스피, 외국인 3천200억 순매수에 3,260대 회복…카카오·삼성전자·대한전선...","link":"http://www.topstarnews.net/news/articleView.html?idxno=14609009","description":"시가총액 상위 종목 가운데에는 카카오[035720](2.58%)와 LG화학[051910](2.43%), 현대차(3.43%) 등이 2% 이상 올랐고, 삼성전자[<b>005930</b>](0.13%)는 8만원선에 턱걸이했다. 이베이코리아 인수 의사를 철회한 네이버... ","datetime":"2021-06-22 07:16:00"},{"title":"코스피, 외인 매수에 상승 마감","link":"http://www.newstomato.com/ReadNews.aspx?no=1053629&inflow=N","description":"코스피 시가총액 상위 종목에서는 삼성전자(<b>005930</b>), 카카오(035720), LG화학(051910), 현대차(005380), 삼성SDI(006400) 등이 상승했다. NAVER(035420)와 삼성바이오로직스(207940)는 소폭 하락했다. 코스닥은 전일보다 0.... ","datetime":"2021-06-22 06:46:00"},{"title":"[코스피 마감] 외국인 순매수 힘입어 3260선 회복","link":"https://news.naver.com/main/read.nhn?mode=LSD&mid=sec&sid1=101&oid=018&aid=0004964880","description":"삼성전자(<b>005930</b>)가 1% 미만으로 소폭 올랐고, SK하이닉스(000660)는 보합으로 마무리됐다. 카카오(035720)는 2.58% 올라 시가총액 70조원으로 마무리됐다. 이베이코리아 인수 불참을 선언한 NAVER(035420)는 1% 넘게... ","datetime":"2021-06-22 06:45:00"},{"title":"중간배당 상장사 늘었다…&quot;변동성 대비 투자 유효&quot;","link":"https://news.naver.com/main/read.nhn?mode=LSD&mid=sec&sid1=101&oid=018&aid=0004964879","description":"삼성전자(<b>005930</b>) 등 중간배당 실시가 확실시되지만 아직 관련 공시를 하지 않은 상장사까지 고려하면 중간배당 실시 기업은 더 늘어날 것으로 보인다. 중간배당을 올해 처음 실시하는 기업은 10개사다.... ","datetime":"2021-06-22 06:44:00"},{"title":"삼성, 베컴 e스포츠팀 스폰서로…1조 시장 정조준","link":"http://www.newstomato.com/ReadNews.aspx?no=1053537&inflow=N","description":"뉴스토마토 = 김광연 기자 | 삼성전자(<b>005930</b>)가 잉글랜드 축구스타 데이비드 베컴이 공동 소유한 영국 e스포츠 회사 '길드 e스포츠'와 손을 잡았다. 유망 게임 업체와 제휴를 통해 자사 게이밍 모니터 '오디세이' 이미지... ","datetime":"2021-06-22 05:26:00"},{"title":"[이데일리N] 삼성전자, 1분기 5G폰 4위…내년엔 애플 이어 2위 전망","link":"https://news.naver.com/main/read.nhn?mode=LSD&mid=sec&sid1=101&oid=018&aid=0004964713","description":"삼성전자(<b>005930</b>)가 글로벌 5G 스마트폰 시장에서 애플과 중국업체에 밀려 올해 1분기 4위에 그쳤지만, 내년 2위까지 오를 것이라는 분석이 나왔습니다. 오늘 시장조사업체 스트래티지 애널리틱스에 따르면... ","datetime":"2021-06-22 05:08:00"},{"title":"[이데일리N] `여름 보너스` 중간배당 상장사, 코로나 전보다 늘었다","link":"https://news.naver.com/main/read.nhn?mode=LSD&mid=sec&sid1=101&oid=018&aid=0004964690","description":"삼성전자(<b>005930</b>) 등 아직 배당 공시를 하지 않은 기업까지 고려하면 중간 배당 기업 수는 더 늘어날 전망입니다. 지난해 코로나19 대응 차원에서 당국이 배당금을 제한했던 금융주도 중간 배당 기대가 커지고... ","datetime":"2021-06-22 04:51:00"},{"title":"[IT큐레이션] 위기의 갤럭시 5G, 판 바꿔야 산다","link":"https://www.econovill.com/news/articleView.html?idxno=537603","description":" 삼성전자(<b>005930</b>) 5G 스마트폰 전략에 경고등이 들어왔다. 세계 최초 5G 상용화 바람을 타고 5G 스마트폰을 발 빠르게 출시했지만 뒤늦게 시장에 뛰어든 애플에 치이고 중국 5G 스마트폰 압박에 고전하고 있기 때문이다.... ","datetime":"2021-06-22 02:24:00"},{"title":"삼성 비스포크 슈드레서, &quot;직접 써보고 선택하세요!&quot;","link":"https://www.econovill.com/news/articleView.html?idxno=537564","description":"출처= 삼성전자 삼성전자(<b>005930</b>)가 자사의 신발관리기 '비스포크 슈드레서'를 직접 경험해 볼 수 있는 다채로운 체험마케팅을 선보인다. 비스포크 슈드레서는 냄새 입자를 효과적으로 털어내는 '에어워시', 냄새... ","datetime":"2021-06-22 02:02:00"},{"title":"삼성 '비스포크 슈드레서'…골프클럽·영화관·호텔에 체험존 마련","link":"https://news.naver.com/main/read.nhn?mode=LSD&mid=sec&sid1=101&oid=018&aid=0004964502","description":"삼성전자(<b>005930</b>)가 신발관리기 ‘비스포크 슈드레서’를 직접 경험해 볼 수 있는 체험마케팅을 선보인다. 삼성전자 모델이 안성베네스트골프클럽에 마련된 신발관리기 ‘비스포크 슈드레서’ 체험존을 소개하고 있다.... ","datetime":"2021-06-22 02:01:00"},{"title":"삼성, 1분기 5G 스마트폰 공급 성장세 1위…中서 점유율 밀려","link":"https://news.naver.com/main/read.nhn?mode=LSD&mid=sec&sid1=105&oid=018&aid=0004964375","description":"삼성이 2021년 1분기에 세계에서 가장 빠르게 성장하는 5G 스마트폰 공급 업체로 나타났다 (자료=스트래티지애널리틱스)[이데일리 이대호 기자] 삼성전자(<b>005930</b>)가 2021년 1분기 기준 5세대 이동통신(5G) 스마트폰 공급... ","datetime":"2021-06-22 00:57:00"},{"title":"코스피, 테이퍼링 불안 완화에 상승 출발…‘3260선’","link":"https://news.naver.com/main/read.nhn?mode=LSD&mid=sec&sid1=101&oid=018&aid=0004964316","description":"삼성전자(<b>005930</b>)와 SK하이닉스(000660)는 1% 안팎으로 상승 중이다. 카카오(035720)가 1% 넘게 오르고 있고, NAVER(035420)와 LG화학(051910)도 1% 미만으로 오름세다. 현대차(005380)는 2%대 오름세를 보여주고 있다. 전일... ","datetime":"2021-06-22 00:16:00"},{"title":"코스피, 개인 매수에 상승 출발","link":"http://www.newstomato.com/ReadNews.aspx?no=1053442&inflow=N","description":"삼성전자(<b>005930</b>), SK하이닉스(000660), 카카오(035720), NAVER(035420), LG화학(051910), 현대차(005380) 등은 상승 중이다. 코스닥은 전일보다 4.48포인트(0.44%) 오른 1015.47에 거래되고 있다. 개인이 185억원을 순매수하고... ","datetime":"2021-06-22 00:12:00"}]