[{"title":"10만전자 간다던 삼성전자, 한 달 만에 다시 ‘7만전자’…외인·기관은 6000...","link":"https://news.naver.com/main/read.nhn?mode=LSD&mid=sec&sid1=101&oid=366&aid=0000736155","description":"대장주 삼성전자(<b>005930</b>)가 한 달여 만에 다시 7만전자로 내려왔다. 외국인과 기관투자자가 동반 순매도에 나서면서 주가를 끌어내렸다. 21일 한국거래소에 따르면 삼성전자는 전거래일보다 600원(0.75%) 하락한... ","datetime":"2021-06-21 09:49:00"},{"title":"[IT Works] 삼성전자·윌라 오디오북·젠하이저 등","link":"http://www.newsprime.co.kr/news/article.html?no=547160","description":"삼성전자(<b>005930</b>)가 21년형 게이밍 모니터 신제품 오디세이 4종을 국내뿐 아니라 전 세계 주요 시장에 출시한다고 21일 밝혔다. 신제품 4종은 오디세이 △G70A(28형) △G50A(27형) △G30A(２７형·２４형)로 출시된다.... ","datetime":"2021-06-21 08:56:00"},{"title":"[부고] 원형석 대한컬링연맹 이사 부친상","link":"http://www.safetimes.co.kr/news/articleView.html?idxno=96795","description":"☎ 02-2030-7919 ■ 이기조 우리은행 본점1기업영업본부장 부친상 ▲이두창 씨 별세, 배춘옥 씨 배우자상, 이재춘(전 삼성전자[<b>005930</b>] 근무)·기화(김포교통 근무)·기주(앙천경찰서 근무)·기조(우리은행... ","datetime":"2021-06-21 08:30:00"},{"title":"[마켓뷰] 코스피, 3240선으로 밀려…외인·기관 2조 가량 순매도","link":"https://news.naver.com/main/read.nhn?mode=LSD&mid=sec&sid1=101&oid=366&aid=0000736130","description":"카카오(035720)는 15만5000원에 보합 마감했고, 삼성전자(<b>005930</b>)는 7만원대로 내려 앉았다. 삼성전자가 7만원대 종가를 기록한 것은 지난달 27일(7만9600원) 이후 17거래일 만이다. 특히 카카오 주가는 장중 급등락을... ","datetime":"2021-06-21 07:48:00"},{"title":"외인·기관, 2조원 팔았다…코스피, 0.8% 하락 마감","link":"http://www.newstomato.com/ReadNews.aspx?no=1053308&inflow=N","description":"시가총액 상위 종목 종목 중 SK하이닉스(000660)(-2.01%), 삼성전자(<b>005930</b>)(-0.75%), 현대차(005380)(-0.85%) 등이 내렸으며 카카오(035720)와 LG화학(051910)은 보합권에서 마무리했다. 삼성바이오로직스(207940)(2.15%)와... ","datetime":"2021-06-21 07:42:00"},{"title":"개인 2조 순매수에도 코스피 0.83% 하락…증시 거래대금 28조원 육박","link":"http://www.topstarnews.net/news/articleView.html?idxno=14608758","description":"시가총액 상위권에서는 SK하이닉스[000660](-2.01%), 포스코[005490](-1.32%), 기아[000270](-1.24%), 삼성전자[<b>005930</b>](-0.75%), KB금융[105560](-2.99%) 등이 하락했다. 한국전력[015760](-6.88%)은 3분기 전기요금이 동결됐다는... ","datetime":"2021-06-21 07:30:00"},{"title":"코스피, 美 조기 긴축 언급 부담에 하락…3240.79 마감","link":"https://www.econovill.com/news/articleView.html?idxno=537512","description":"대장주인 삼성전자(<b>005930</b>)는 전 거래일 대비 600원(0.75%) 내린 7만9,900원에 거래를 마쳤다. SK하이닉스(000660)(-2.01%)도 3거래일 연속 하락했다. 카카오(035720)(-)는 보합, NAVER(035420)(-0.25%)는 하락했다. LG화학(051910)... ","datetime":"2021-06-21 07:26:00"},{"title":"[마감시황] 하락폭 키우던 코스피, 개인 대량 매수에 3,240선 회복","link":"https://news.naver.com/main/read.nhn?mode=LSD&mid=sec&sid1=101&oid=011&aid=0003926168","description":"삼성전자(<b>005930</b>)는 전일 대비 0.75%(600원) 내린 7만9,900만원에 장을 마감했고, SK하이닉스(000660)(-2.01%), NAVER(035420)(-0.25%), 현대차(-0.85%) 등도 하락했다. 반면 삼성바이오로직스(207940)(2.15%), 삼성SDI(1.04... ","datetime":"2021-06-21 07:15:00"},{"title":"삼성D, 창사 첫 파업 돌입…총파업 확대 시사","link":"http://www.newstomato.com/ReadNews.aspx?no=1053296&inflow=N","description":"이번 삼성디스플레이의 파업은 지난해 5월 무노조 경영 철폐를 선언한 이재용 삼성전자(<b>005930</b>) 부회장 발언이 있은지 약 1년 만이다. 이 부회장 발언 이후 그간 계열사 내 노사관계 자문그룹을 구성하고 노사 관계 개선에... ","datetime":"2021-06-21 07:08:00"},{"title":"[코스피 마감]델타변이·테이퍼링 언급 부담에 하락…‘3240’","link":"https://news.naver.com/main/read.nhn?mode=LSD&mid=sec&sid1=101&oid=018&aid=0004963897","description":"삼성전자(<b>005930</b>)(-0.75%), SK하이닉스(000660)(-2.01%), NAVER(035420)(-0.25%), 현대차(005380)(-0.85%) 등이 하락했다. 카카오(035720)는 한때 15만9500원까지 올라 52주 최고가를 경신했지만 보합에서 마무리됐다. 삼성바이오로직스... ","datetime":"2021-06-21 06:52:00"},{"title":"삼성 95만원 UHD 게이밍 모니터 선보여···신제품 오디세이 4종 공개","link":"https://news.naver.com/main/read.nhn?mode=LSD&mid=sec&sid1=105&oid=011&aid=0003926140","description":"삼성전자(<b>005930</b>)가 100만 원이 채 안 되는 고해상도(UHD) 게이밍 모니터를 내놓았다. 고스펙 게이밍 모니터 시장에서 1위를 굳히기 위한 포석으로 보인다. 삼성전자는 21일 2021년형 게이밍 모니터 신제품... ","datetime":"2021-06-21 06:37:00"},{"title":"[부고] 이기조(우리은행 본점1기업영업본부장)씨 부친상","link":"http://www.jeonmae.co.kr/news/articleView.html?idxno=844389","description":"▲ 이두창 씨 별세, 배춘옥 씨 배우자상, 이재춘(전 삼성전자[<b>005930</b>] 근무)·기화(김포교통 근무)·기주(앙천경찰서 근무)·기조(우리은행 본점1기업영업본부장)·선분·귀분 씨 부친상, 안기혁(리베라호텔 근무)... ","datetime":"2021-06-21 05:38:00"},{"title":"&lt;오늘의 부고&gt;","link":"http://www.ajunews.com/view/20210621112608452","description":"☎ 02-2030-7919 ▲이두창씨 별세, 배춘옥씨 남편상, 이재춘(전 삼성전자[<b>005930</b>] 근무)·기화(김포교통 근무)·기주(앙천경찰서 근무)·기조(우리은행 본점1기업영업본부장)·선분·귀분씨 부친상, 안기혁... ","datetime":"2021-06-21 05:08:00"},{"title":"[오후시황] 조기 긴축 발언에 코스피, 1% 이상 낙폭···3,230선 등락","link":"https://news.naver.com/main/read.nhn?mode=LSD&mid=sec&sid1=101&oid=011&aid=0003926084","description":"삼성전자(<b>005930</b>)는 전일 대비 0.87%(700원) 내린 7만9,800만원에 거래 중이고, SK하이닉스(000660)(-2.41%), NAVER(035420)(-0.25%), LG화학(051910)(-0.24%), 현대차(-0.43%) 등도 하락세다. 같은 시각 코스닥 지수 역시 전일... ","datetime":"2021-06-21 05:04:00"},{"title":"삼성전자, 21년형 게이밍 모니터 '오디세이' 4종 출시","link":"http://www.koreastocknews.com/news/articleView.html?idxno=64323","description":" 삼성전자(<b>005930</b>, 대표 김기남·김현석·고동진)는 21년형 게이밍 모니터 신제품 '오디세이(Odyssey)' 4종을 국내를 포함한 전 세계에 출시한다고 21일 밝혔다.","datetime":"2021-06-21 04:36:00"},{"title":"[특징주] LG디스플레이, 삼성전자 OLED 패널 공급 소식에 강세","link":"https://www.econovill.com/news/articleView.html?idxno=537452","description":"출처=LG디스플레이 LG디스플레이(034220)가 삼성전자(<b>005930</b>)에 유기발광다이오드(OLED) 패널 공급한다는 소식에 강세를 보이고 있다. 액정표시장치(LCD) 패널 가격 인상으로 LCD TV 수익성이 악화되자 OLED 시장으로... ","datetime":"2021-06-21 03:56:00"},{"title":"[부고] 최윤겸(한국프로축구연맹 기술위원) 부친상 외","link":"http://www.readersnews.com/news/articleView.html?idxno=103449","description":"삼성전자[<b>005930</b>] 근무)·기화(김포교통 근무)·기주(앙천경찰서 근무)·기조(우리은행 본점1기업영업본부장)·선분·귀분 씨 부친상, 안기혁(리베라호텔 근무)·이병규(바로디자인 대표)씨 장인상 = 20일 오후 7시... ","datetime":"2021-06-21 02:18:00"},{"title":"‘제2의 전성기' 태블릿, 애플·삼성 ‘점유율 57%’로 시장 양분","link":"https://news.naver.com/main/read.nhn?mode=LSD&mid=sec&sid1=105&oid=366&aid=0000735903","description":"이 가운데 애플과 삼성전자(<b>005930</b>)는 적극적인 신제품 출시, 공격 마케팅에 힘입어 글로벌 태블릿 시장 점유율 50% 이상을 점유하고 있는 것으로 나타났다. 21일 시장조사기관 카운터포인트 리서치의 태블릿 시장... ","datetime":"2021-06-21 02:16:00"},{"title":"삼성전자, UHD 지원 게이밍 모니터 '2021년형 오디세이' 출시","link":"https://news.naver.com/main/read.nhn?mode=LSD&mid=sec&sid1=101&oid=018&aid=0004963479","description":"삼성전자(<b>005930</b>)가 2021년형 게이밍 모니터 신제품 ‘오디세이(Odyssey)’ 4종을 국내를 포함한 전 세계 주요 시장에 21일 출시한다고 밝혔다. 삼성전자 모델이 서울 시내 한 스튜디오에서 삼성전자의 신제품... ","datetime":"2021-06-21 02:01:00"},{"title":"'압도적 몰입감' 삼성전자, 게이밍 모니터 오디세이 2021년형 제품 출시","link":"https://www.econovill.com/news/articleView.html?idxno=537423","description":"출처= 삼성전자 삼성전자(<b>005930</b>)가 2021년형 게이밍 모니터 신제품 '오디세이(Odyssey)' 4종을 국내를 포함한 전 세계 주요 시장에 21일 출시한다. 오디세이 G70A (28형)는 미래 지향적 디자인과 오디세이 최초의 UHD... ","datetime":"2021-06-21 02:00:00"},{"title":"코스피, 0.9%대 약세…카카오 장중 반락","link":"https://news.naver.com/main/read.nhn?mode=LSD&mid=sec&sid1=101&oid=366&aid=0000735874","description":"삼성전자(<b>005930</b>)는 7만원대에서 거래되고 있다. 코스닥지수는 전거래일보다 5.03포인트(0.50%) 하락한 1010.85를 기록하고 있다. 이날 1014.59에 하락 출발한 지수는 장중 1000 후반대와 1010 초반대 사이에서... ","datetime":"2021-06-21 01:56:00"},{"title":"[마켓인]플래티어, 증권신고서 제출…코스닥 상장 본격화","link":"https://news.naver.com/main/read.nhn?mode=LSD&mid=sec&sid1=101&oid=018&aid=0004963394","description":"플래티어는 롯데, 현대자동차(005380), 삼성전자(<b>005930</b>), SK하이닉스(000660), 넥센(005720), 우리은행, 휠라코리아, 이니스프리 등 다양한 분야의 유명 기업들과 오랜 기간 협업해왔다. 6월 현재 플래티어의 고객사는 약... ","datetime":"2021-06-21 00:49:00"},{"title":"[오전시황] 美 증시 부진에 숨고르기 들어간 코스피···전일 대비 0.96% ↓","link":"https://news.naver.com/main/read.nhn?mode=LSD&mid=sec&sid1=101&oid=011&aid=0003925908","description":"삼성전자(<b>005930</b>)는 전일 대비 0.62%(500원) 내린 8만원에 거래 중이고, SK하이닉스(000660)(-1.61%), LG화학(-0.24%), 삼성바이오로직스(-0.6%), 현대차(-0.43%) 등도 하락세다. 그러나 카카오(035720)(1.61%), NAVER(035420)(0.13... ","datetime":"2021-06-21 00:47:00"},{"title":"[부고] 이기조(우리은행 본점1기업영업본부장)씨 부친상 외","link":"https://www.inthenews.co.kr/news/article.html?no=36379","description":"▲ 이두창 씨 별세, 배춘옥 씨 배우자상, 이재춘(전 삼성전자[<b>005930</b>] 근무)·기화(김포교통 근무)·기주(앙천경찰서 근무)·기조(우리은행 본점1기업영업본부장)·선분·귀분 씨 부친상, 안기혁(리베라호텔 근무)... ","datetime":"2021-06-21 00:40:00"},{"title":"삼성전자, 장중 7만원대…3거래일째 약세","link":"https://news.naver.com/main/read.nhn?mode=LSD&mid=sec&sid1=101&oid=366&aid=0000735736","description":"삼성전자(<b>005930</b>)가 장중 7만원대로 떨어지며 약세다. 21일 한국거래소에 따르면 오전 9시 16분 기준 삼성전자는 전거래일보다 600원(0.75%) 하락한 7만9900원에 거래됐다. 삼성전자는 지난 17일부터 3거래일 연속... ","datetime":"2021-06-21 00:23:00"},{"title":"코스피, 테이퍼링 압박·델타변이 우려에 하락 출발…‘3247선’","link":"https://news.naver.com/main/read.nhn?mode=LSD&mid=sec&sid1=101&oid=018&aid=0004963318","description":"삼성전자(<b>005930</b>)가 1% 미만, SK하이닉스(000660)가 2%대 하락 중이다. NAVER(035420), LG화학(051910), 삼성바이오로직스(207940), 삼성SDI(006400) 등이 1% 미만으로 빠지고 있다. 지난 18일(미 동부시간) 뉴욕증권거래소(NYSE)... ","datetime":"2021-06-21 00:14:00"},{"title":"코스피, 외인·기관 매도에 3240선 하락 출발","link":"http://www.newstomato.com/ReadNews.aspx?no=1053088&inflow=N","description":"SK하이닉스(000660)가 2% 넘게 빠지고 있으며 삼성전자(<b>005930</b>)(-0.75%), 삼성SDI(006400)(-1.34%) 등도 내리고 있다. 이날 같은 시각 코스닥 지수는 전장 대비 3.67포인트(-0.36%) 하락한 1012.21에 거래되고 있다. 코스닥... ","datetime":"2021-06-21 00:14:00"}]