[{"title":"LG 기술 사들인 유럽 특허괴물, 삼성전자에 소송","link":"https://news.naver.com/main/read.nhn?mode=LSD&mid=sec&sid1=101&oid=011&aid=0003906385","description":"삼성전자(<b>005930</b>)가 LG이노텍(011070) 특허 기술을 사들인 유럽 특허괴물 ‘스크래모지’로부터 미국에서 특허 침해 소송을 당했다. 모바일사업부 철수를 선언한 LG전자(066570)의 특허까지 시장에 풀리면 글로벌... ","datetime":"2021-05-05 09:05:00"},{"title":"특허괴물, LG 5G 표준 기술도 눈독···韓기업에 전방위 소송 예고","link":"https://news.naver.com/main/read.nhn?mode=LSD&mid=sec&sid1=105&oid=011&aid=0003906382","description":"LG전자(066570) 스마트폰 사업 철수에 따른 특허 기술 유출 우려가 예고된 가운데 LG이노텍(011070)의 무선 충전 특허를 인수한 글로벌 특허전문업체(NPE)가 삼성전자(<b>005930</b>)를 상대로 미국에서 특허침해 소송을 냈다.... ","datetime":"2021-05-05 08:54:00"},{"title":"국산 첫 자동차 MCU, 삼성 파운드리서 생산","link":"https://news.naver.com/main/read.nhn?mode=LSD&mid=sec&sid1=101&oid=011&aid=0003906342","description":"지난달부터 삼성전자(<b>005930</b>)의 위탁생산 파운드리를 통해 시범 생산했다. 업계에서는 삼성전자가 중소 팹리스(반도체 설계전문)를 통해 국내 완성차 업계를 우회 지원한 것으로 보고 있다. 진입 장벽이 높은 차량용... ","datetime":"2021-05-05 07:59:00"},{"title":"LG폰 특허 사들인 글로벌 특허괴물, 삼성전자에 특허침해 소송","link":"https://news.naver.com/main/read.nhn?mode=LSD&mid=sec&sid1=105&oid=366&aid=0000712498","description":"LG이노텍이 매각한 무선충전 관련 특허, 삼성폰 겨냥 지난 2월 LG 스마트폰의 특허를 사들였던 글로벌 ‘특허괴물’이 최근 삼성전자(<b>005930</b>)를 상대로 특허침해 소송을 제기했다. 삼성전자가 해당 특허를... ","datetime":"2021-05-05 07:50:00"},{"title":"'삼성전자 보유' 미성년자 1년새 6배 늘어 11만명","link":"https://news.naver.com/main/read.nhn?mode=LSD&mid=sec&sid1=101&oid=011&aid=0003906334","description":"삼성전자(<b>005930</b>) 주식을 보유한 20대 미만 미성년 주주 수가 1년간 6배 이상 증가해 11만 명을 넘어섰다. 부모들이 어린 자녀에서 주식을 사주거나 청소년들이 직접 주식에 투자하는 데 대한 관심이 늘어난... ","datetime":"2021-05-05 07:40:00"},{"title":"① 4년전처럼 반도체 초호황인데···삼성, TSMC 공세에 파운드리 격차 더 벌...","link":"https://news.naver.com/main/read.nhn?mode=LSD&mid=sec&sid1=101&oid=011&aid=0003906331","description":"하지만 삼성전자(<b>005930</b>)가 기회를 살리지 못할 것이라는 우려가 커지고 있다. 파운드리(반도체 위탁 생산) 분야에서는 선두 주자인 대만 TSMC에 투자 규모에서 밀려 추격에 어려움을 겪고 있고, ‘초격차’ 전략으로... ","datetime":"2021-05-05 07:36:00"},{"title":"이재용 '대국민 사과' 이끈 준법위…'실효성' 입증 노력 계속","link":"https://news.naver.com/main/read.nhn?mode=LSD&mid=sec&sid1=101&oid=018&aid=0004921373","description":"이재용 삼성전자(<b>005930</b>) 부회장의 ‘국정농단’ 재판 파기환송심 재판부의 요구로 탄생한 ‘삼성 준법감시위원회(준법위)’는 지난 2월로 출범 1주년을 맞았다. 준법위는 출범 이후 파기환송심 재판이 끝나기까지 1년이 채... ","datetime":"2021-05-05 06:44:00"},{"title":"이재용 無노조 경영 폐기 선언 후 新노사문화 정립 노력","link":"https://news.naver.com/main/read.nhn?mode=LSD&mid=sec&sid1=101&oid=018&aid=0004921374","description":"이재용 삼성전자(<b>005930</b>) 부회장이 작년 5월 삼성전자 설립 51년 만에 무노조 경영 폐기를 선언한 뒤 삼성에 새로운 노사문화가 정립되고 있다. 사측은 노사관계자문그룹 등 별도의 조직을 구성해 노동조합과 소통에... ","datetime":"2021-05-05 06:44:00"},{"title":"한달 만에 돌아온 기관…삼성전자 9만전자 갈까","link":"https://news.naver.com/main/read.nhn?mode=LSD&mid=sec&sid1=101&oid=018&aid=0004921369","description":"국민 대장주 삼성전자(<b>005930</b>) 주식에 대해 기관이 22거래일 만에 순매수세를 보였다. 삼성전자는 지난 1월 9만원을 돌파한 이후 최근까지 횡보세를 보이다 이날 근 한 달 만에 1%대 상승률을 기록했다. 이 가운데 미국발... ","datetime":"2021-05-05 06:33:00"},{"title":"(영상)D램값 고공행진…삼성전자·하이닉스 '방긋'","link":"http://www.newstomato.com/ReadNews.aspx?no=1042263&inflow=N","description":"삼성전자(<b>005930</b>)와 SK하이닉스(000660)는 전 세계 D램 시장에서 70%에 달하는 시장 점유율을 기록하고 있습니다. 삼성전자와 SK하이닉스의 실적이 크게 개선될 것이라고 기대하는 이윱니다. 트렌드포스는 올 하반기에도... ","datetime":"2021-05-05 03:48:00"},{"title":"계속 오르는 반도체 값…삼성전자·하이닉스 즐거운 비명","link":"http://www.newstomato.com/ReadNews.aspx?no=1042226&inflow=N","description":"이에 따라 전 세계 D램 시장 점유율 70%를 차지하는 삼성전자(<b>005930</b>)와 SK하이닉스(000660)의 실적 개선이 기대된다. 5일 관련업계에 따르면 D램 가격은 비수기인 1분기부터 상승세를 보였다. 대만의 시장조사기관... ","datetime":"2021-05-05 03:32:00"},{"title":"“뽀로로도 삼성 에어드레서 쓴다”…어린이날 맞이 유튜브 광고 인기","link":"https://news.naver.com/main/read.nhn?mode=LSD&mid=sec&sid1=105&oid=366&aid=0000712456","description":"삼성전자(<b>005930</b>)가 5일 어린이날을 맞아 인기 애니메이션 뽀로로와 컬래버레이션한 의류관리기기 ‘에어드레서’ 광고 영상이 유튜브에서 인기를 얻고 있다. 뽀로로와 삼성전자 유튜브 채널에 지난 3일 올라온 이 영상은... ","datetime":"2021-05-05 01:41:00"},{"title":"이낙연 &quot;이번 또는 다음 정부서 대통령 직속 백신개발위 운영해야&quot;","link":"https://news.naver.com/main/read.nhn?mode=LSD&mid=sec&sid1=100&oid=011&aid=0003906224","description":"그는 “어제 발간기념식에서 저는 대한민국을 미국, 영국, 독일에 이은 백신제약 4강으로 도약시키겠다고 다짐했다”며 “반도체의 삼성전자(<b>005930</b>)와 SK하이닉시, 자동차의 현대, 전기차 배터리의 LG화학(051910) 같은... ","datetime":"2021-05-05 00:57:00"}]