[{"title":"'시대흐름 역행' 車판매노조..기아 EV6 온라인예약도 반대","link":"https://news.naver.com/main/read.nhn?mode=LSD&mid=sec&sid1=103&oid=018&aid=0004879493","description":"반면 현대차(<b>005380</b>)·기아는 국내에서 판매 노조의 반대에 부딪혀 온라인 판매 관련 사업을 전혀 하지 못하고 있다. EV6의 온라인 사전예약처럼 판매 여부와 관계없이 ‘온라인’이란 말만 나와도 과민반응을 보이기... ","datetime":"2021-03-18 07:58:00"},{"title":"코로나에도 미래 대비한 정의선‥현대차그룹, 지난해 투자 두자릿수 확대","link":"https://news.naver.com/main/read.nhn?mode=LSD&mid=sec&sid1=103&oid=018&aid=0004879491","description":"(사진=현대차그룹 제공) 현대차그룹 ‘빅3’ 현대자동차(<b>005380</b>)와 기아(기아차(000270)), 현대모비스(012330)가 지난해 코로나19 여파와 세타엔진 관련 대규모 품질 충당금에도 불구하고 미래사업 역량 확보를 위해 투자에... ","datetime":"2021-03-18 07:53:00"},{"title":"코스피, 'FOMC 훈풍' 외국인‧기관 매수에 상승…3054.39 마감","link":"https://www.econovill.com/news/articleView.html?idxno=523894","description":"NAVER(035420)(5.22%), LG화학(051910)(0.47%), 현대차(<b>005380</b>)(0.86%)도 상승했다. 삼성바이오로직스(207940)(0.42%), 삼성SDI(006400)(3.60%), 카카오(035720)(2.68%), 기아차(000270)(3.66%) 올랐다. 셀트리온(068270)(0.51%)은 약세를... ","datetime":"2021-03-18 07:24:00"},{"title":"폭스바겐은 '각형' 테슬라는 '원통형'… 전기차 '배터리 표준' 경쟁","link":"https://news.naver.com/main/read.nhn?mode=LSD&mid=sec&sid1=103&oid=366&aid=0000686795","description":"글로벌 완성차 업체 중에서는 BMW, 벤츠 등 독일 업체들이 각형 배터리를 쓰고, 현대차(<b>005380</b>)·기아(기아차(000270)), GM, 포드 등은 파우치형을 사용해왔다. 원통형은 테슬라가 선호한다. 폭스바겐이 각형 배터리를 선택한... ","datetime":"2021-03-18 07:08:00"},{"title":"코스피, 미국 FOMC 안도감에 상승 마감","link":"http://www.newstomato.com/ReadNews.aspx?no=1032013","description":"시가총액 상위 종목 중에선 삼성전자(005930)(0.73%), SK하이닉스(000660)(1.43%), #네이버(5.22%), LG화학(051910)(0.47%), 현대차(<b>005380</b>)(0.86%) 등은 상승했다. 반면 셀트리온(068270)(-0.51%), LG전자(066570)(-1.58... ","datetime":"2021-03-18 07:06:00"},{"title":"[코스피 마감]`파월 효과`…금리 상승 우려 떨치며 `3060선` 회복","link":"https://news.naver.com/main/read.nhn?mode=LSD&mid=sec&sid1=101&oid=018&aid=0004879389","description":"현대차(<b>005380</b>), 삼성바이오로직스(207940), 삼성SDI(006400), 카카오(035720) 등 시가총액 1~9위가 모두 상승... 대원화성은 현대차(<b>005380</b>)의 전기차 ‘아이오닉5’에 친환경 시트 소재를 공급한다는 소식에 주가가... ","datetime":"2021-03-18 06:54:00"},{"title":"[포토]故정주영 20주기…아산 흉상 계동사옥 이전","link":"https://news.naver.com/main/read.nhn?mode=LSD&mid=sec&sid1=101&oid=018&aid=0004879372","description":"본관 1층에 아산 흉상을 이전하고 창업주 아산 20주기 추모공간을 마련했다. 현대차그룹 직원들이 현대차(<b>005380</b>) 그룹 계동사옥 1층에 설치된 아산 흉상 앞에서 사진을 찍으며 업적과 정신을 되새기고 있다. 이혜라","datetime":"2021-03-18 06:47:00"},{"title":"현대차-쉘, 글로벌 파트너십 5년 연장...미래모빌리티 협력 기대","link":"https://news.naver.com/main/read.nhn?mode=LSD&mid=sec&sid1=103&oid=366&aid=0000686693","description":"글로벌 고객만족도 개선과 서비스 경쟁력 강화를 위해 지난 2005년부터 공동 마케팅 활동을 진행해 오고 있는 현대자동차(<b>005380</b>)와 에너지기업 로열 더치 쉘 그룹(이하 쉘)이 2026년까지 글로벌 비즈니스 파트너십 계약을... ","datetime":"2021-03-18 05:31:00"},{"title":"범 현대家 차분한 분위기 속 아산 정신 기린다","link":"https://news.naver.com/main/read.nhn?mode=LSD&mid=sec&sid1=101&oid=011&aid=0003884969","description":"정의선 현대차(<b>005380</b>)그룹 회장은 21일 이전에 선영을 찾아 참배하고 다른 그룹들은 21일 전후로 선영을 찾을 예정이다. 22일부터는 범현대가 차원의 20주기 사진전이 계동 사옥에서 진행된다. 기업별 추모 행사도... ","datetime":"2021-03-18 05:27:00"},{"title":"현대차, 쉘과 협력 5년간 연장..미래모빌리티로 협업 확대","link":"https://news.naver.com/main/read.nhn?mode=LSD&mid=sec&sid1=103&oid=018&aid=0004879200","description":"지난 2005년부터 글로벌 고객만족도 개선과 서비스 경쟁력 강화를 위한 공동 마케팅 활동을 진행해 오고 있는 현대자동차(<b>005380</b>)와 에너지기업 로열 더치 쉘 그룹(이하 쉘)이 2026년까지 글로벌 비즈니스 파트너십 계약을... ","datetime":"2021-03-18 05:11:00"},{"title":"현대차-쉘, 글로벌 비즈니스 파트너십 연장","link":"http://www.newsprime.co.kr/news/article.html?no=537230","description":"현대자동차(<b>005380</b>)가 에너지 기업인 로열 더치 쉘 그룹(Royal Dutch Shell Group, 이하 쉘)과 글로벌 비즈니스 파트너십 계약을 연장한다. 18일 현대차는 현대모터스튜디오 고양에 중계센터를 설치하고, 쉘 관계자들을 온라인... ","datetime":"2021-03-18 04:34:00"},{"title":"Seven out of 10 hydrogen fueled cars sold worldwide last year were Hyund...","link":"http://www.g-enews.com/ko-kr/news/article/news_all/202103180941521868c4c1a19e2e_9/article.html","description":"Hyundai Motor Company [<b>005380</b>] took the unrivaled first place in the worldwide hydrogen fuel cell vehicle sales last year. According to SNE Research, an energy-specialized market research firm on... ","datetime":"2021-03-18 03:17:00"},{"title":"&quot;인사이드 아웃&quot; 프리미엄 크루즈 닮은 현대차 '스타리아'","link":"http://www.newsprime.co.kr/news/article.html?no=537224","description":"현대자동차(<b>005380</b>)의 새로운 MPV(Multi-Purpose Vehicle, 다목적 차량), 프리미엄 크루저(cruiser) '스타리아'의 내·외장 이미지가 18일 공개됐다. 스타리아는 현대차의 미래 모빌리티 디자인 테마인 인사이드 아웃이 반영된... ","datetime":"2021-03-18 02:19:00"},{"title":"[특징주]대원화성, 현대차 '아이오닉5'에 친환경 시트 소재 공급…'급등'","link":"https://news.naver.com/main/read.nhn?mode=LSD&mid=sec&sid1=101&oid=018&aid=0004878936","description":"대원화성(024890)이 현대차(<b>005380</b>)의 전기차 ‘아이오닉5’에 친환경 시트 소재를 공급한다는 소식에 주가가 급등하고 있다. 18일 마켓포인트에 따르면 오전 10시 20분 현재 대원화성은 전 거래일 대비 21.76%(445원) 오른... ","datetime":"2021-03-18 01:23:00"},{"title":"FOMC 결과에 안도한 코스피, 1%대 상승…3080선","link":"https://news.naver.com/main/read.nhn?mode=LSD&mid=sec&sid1=101&oid=018&aid=0004878834","description":"시가총액 1,2위인 삼성전자(005930)가 1% 안팎 상승하는 것을 포함해 NAVER(035420), LG화학(051910), 삼성전자우(005935), 현대차(<b>005380</b>), 삼성바이오로직스(207940), 삼성SDI(006400), 카카오(035720), 셀트리온(068270) 등도 모두... ","datetime":"2021-03-18 00:29:00"},{"title":"현대차, 프리미엄 크루저 '스타리아' 내외관 디자인 공개","link":"https://news.naver.com/main/read.nhn?mode=LSD&mid=sec&sid1=103&oid=366&aid=0000686268","description":"우주선을 연상시키는 외관에 넓은 실내공간을 갖춘 현대차(<b>005380</b>)의 새로운 다목적 차량(MPV·Multi-Purpose Vehicle) ‘스타리아’의 내∙외장 모습이 공개됐다. 스타리아는 일반모델과 고급모델 ‘스타리아 라운지’로... ","datetime":"2021-03-18 00:06:00"}]