[{"date":"2021-03-06 23:18:25","message":"[2021-03-06 23:18:25] INFO: ⚡️  NEWS DATA CREATION COMPLETE (005380)"},{"date":"2021-03-06 23:18:25","message":"[2021-03-06 23:18:25] INFO: ⚡️  NEWS DATA CREATION COMPLETE (005930)"},{"date":"2021-03-06 23:18:25","message":"[2021-03-06 23:18:25] INFO: ⚡️ STOCK DATA CREATION COMPLETE (005380)"},{"date":"2021-03-06 23:18:25","message":"[2021-03-06 23:18:25] INFO: ⚡️ STOCK DATA CREATION COMPLETE (005930)"},{"date":"2021-03-05 23:17:37","message":"[2021-03-05 23:17:37] INFO: ⚡️  NEWS DATA CREATION COMPLETE (005930)"},{"date":"2021-03-05 23:17:37","message":"[2021-03-05 23:17:37] INFO: ⚡️  NEWS DATA CREATION COMPLETE (005380)"},{"date":"2021-03-05 23:17:36","message":"[2021-03-05 23:17:36] INFO: ⚡️ STOCK DATA CREATION COMPLETE (005380)"},{"date":"2021-03-05 23:17:36","message":"[2021-03-05 23:17:36] INFO: ⚡️ STOCK DATA CREATION COMPLETE (005930)"},{"date":"2021-03-04 23:17:55","message":"[2021-03-04 23:17:55] INFO: ⚡️  NEWS DATA CREATION COMPLETE (005930)"},{"date":"2021-03-04 23:17:55","message":"[2021-03-04 23:17:55] INFO: ⚡️  NEWS DATA CREATION COMPLETE (005380)"},{"date":"2021-03-04 23:17:55","message":"[2021-03-04 23:17:55] INFO: ⚡️ STOCK DATA CREATION COMPLETE (005930)"},{"date":"2021-03-04 23:17:55","message":"[2021-03-04 23:17:55] INFO: ⚡️ STOCK DATA CREATION COMPLETE (005380)"},{"date":"2021-03-03 23:17:47","message":"[2021-03-03 23:17:47] INFO: ⚡️  NEWS DATA CREATION COMPLETE (005380)"},{"date":"2021-03-03 23:17:47","message":"[2021-03-03 23:17:47] INFO: ⚡️  NEWS DATA CREATION COMPLETE (005930)"},{"date":"2021-03-03 23:17:47","message":"[2021-03-03 23:17:47] INFO: ⚡️ STOCK DATA CREATION COMPLETE (005380)"},{"date":"2021-03-03 23:17:47","message":"[2021-03-03 23:17:47] INFO: ⚡️ STOCK DATA CREATION COMPLETE (005930)"},{"date":"2021-03-02 23:14:46","message":"[2021-03-02 23:14:46] INFO: ⚡️  NEWS DATA CREATION COMPLETE (005930)"},{"date":"2021-03-02 23:14:46","message":"[2021-03-02 23:14:46] INFO: ⚡️  NEWS DATA CREATION COMPLETE (005380)"},{"date":"2021-03-02 23:14:46","message":"[2021-03-02 23:14:46] INFO: ⚡️ STOCK DATA CREATION COMPLETE (005380)"},{"date":"2021-03-02 23:14:46","message":"[2021-03-02 23:14:46] INFO: ⚡️ STOCK DATA CREATION COMPLETE (005930)"},{"date":"2021-03-01 23:17:27","message":"[2021-03-01 23:17:27] INFO: ⚡️  NEWS DATA CREATION COMPLETE (005380)"},{"date":"2021-03-01 23:17:27","message":"[2021-03-01 23:17:27] INFO: ⚡️  NEWS DATA CREATION COMPLETE (005930)"},{"date":"2021-03-01 23:17:27","message":"[2021-03-01 23:17:27] INFO: ⚡️ STOCK DATA CREATION COMPLETE (005380)"},{"date":"2021-03-01 23:17:27","message":"[2021-03-01 23:17:27] INFO: ⚡️ STOCK DATA CREATION COMPLETE (005930)"}]